fuzzy_df/__init__.py
fuzzy_df/match.py
fuzzy_df/merge.py
fuzzy_df/config/__init__.py
fuzzy_df/config/builder.py
fuzzy_df-0.2.0.dist-info/licenses/LICENSE
fuzzy_df-0.2.0.dist-info/METADATA
fuzzy_df-0.2.0.dist-info/WHEEL
fuzzy_df-0.2.0.dist-info/top_level.txt
fuzzy_df-0.2.0.dist-info/RECORD
