Metadata-Version: 2.4
Name: fuzzy-df
Version: 0.2.0
Summary: Fuzzy merging and matching utilities for pandas Dataframes.
Author-email: Iman-Budi Pranakasih <ibpranakasih@gmail.com>
License-Expression: MIT
Project-URL: Homepage, https://github.com/ibpme/fuzzy-df
Project-URL: Repository, https://github.com/ibpme/fuzzy-df
Project-URL: Issues, https://github.com/ibpme/fuzzy-df/issues
Keywords: fuzzy,pandas,dataframe,matching,merging
Classifier: Development Status :: 3 - Alpha
Classifier: Intended Audience :: Developers
Classifier: Programming Language :: Python :: 3.10
Classifier: Programming Language :: Python :: 3.11
Classifier: Programming Language :: Python :: 3.12
Classifier: Programming Language :: Python :: 3.13
Classifier: Topic :: Software Development :: Libraries :: Python Modules
Classifier: Topic :: Scientific/Engineering :: Information Analysis
Requires-Python: >=3.10
License-File: LICENSE
Requires-Dist: pandas>=2.2.3
Requires-Dist: rapidfuzz>=3.12.2
Dynamic: license-file
